baltoslav/__init__.py
baltoslav/ai.py
baltoslav/game.py
Baltoslav-1.0.3.dist-info/LICENSE
Baltoslav-1.0.3.dist-info/METADATA
Baltoslav-1.0.3.dist-info/WHEEL
Baltoslav-1.0.3.dist-info/top_level.txt
Baltoslav-1.0.3.dist-info/RECORD
